LICENSE
README.md
setup.py
aep.egg-info/PKG-INFO
aep.egg-info/SOURCES.txt
aep.egg-info/dependency_links.txt
aep.egg-info/entry_points.txt
aep.egg-info/namespace_packages.txt
aep.egg-info/requires.txt
aep.egg-info/top_level.txt
aep.egg-info/zip-safe
aep/tools/__init__.py
aep/tools/config.py
aep/tools/format_json.py
aep/tools/generate.py
aep/tools/promise_search.py
aep/tools/promise_usage.py
aep/tools/show_bundle.py
aep/tools/show_promise.py
aep/tools/show_technique.py
aep/tools/libs/__init__.py
aep/tools/libs/data.py
aep/tools/libs/libgenerate.py
aep/tools/libs/types.py