Metadata-Version: 2.1
Name: aep
Version: 0.1.4
Summary: Adversary Emulation Planner (AEP)..
Home-page: https://github.com/mnemonic-no/aep
Author: mnemonic AS
Author-email: opensource@mnemonic.no
License: MIT
Keywords: aep,attack,mnemonic
Platform: UNKNOWN
Classifier: Development Status :: 4 - Beta
Classifier: Topic :: Utilities
Classifier: License :: OSI Approved :: ISC License (ISCL)
Requires-Python: >=3.6, <4
License-File: LICENSE
